pyxdcc/__init__.py
pyxdcc/pyxdcc.py
pyxdcc_cli-0.1.0.dist-info/LICENSE
pyxdcc_cli-0.1.0.dist-info/METADATA
pyxdcc_cli-0.1.0.dist-info/WHEEL
pyxdcc_cli-0.1.0.dist-info/entry_points.txt
pyxdcc_cli-0.1.0.dist-info/top_level.txt
pyxdcc_cli-0.1.0.dist-info/RECORD
